proyecto_alfa/__init__.py
proyecto_alfa/main.py
proyecto_alfa-0.1.0.dist-info/METADATA
proyecto_alfa-0.1.0.dist-info/WHEEL
proyecto_alfa-0.1.0.dist-info/RECORD
