Metadata-Version: 2.1
Name: proyecto-alfa
Version: 0.1.0
Summary: 
Author: david
Author-email: davidmbq@gmail.com
Requires-Python: >=3.11,<4.0
Classifier: Programming Language :: Python :: 3
Classifier: Programming Language :: Python :: 3.11
Classifier: Programming Language :: Python :: 3.12
Requires-Dist: pandas (>=2.2.2,<3.0.0)
Requires-Dist: requests (>=2.31.0,<3.0.0)
